flake8_comprehensions/__init__.py
flake8_comprehensions/py.typed
flake8_comprehensions-3.16.0.dist-info/LICENSE
flake8_comprehensions-3.16.0.dist-info/METADATA
flake8_comprehensions-3.16.0.dist-info/WHEEL
flake8_comprehensions-3.16.0.dist-info/entry_points.txt
flake8_comprehensions-3.16.0.dist-info/top_level.txt
flake8_comprehensions-3.16.0.dist-info/RECORD
