Metadata-Version: 2.1
Name: flake8-comprehensions
Version: 3.16.0
Summary: A flake8 plugin to help you write better list/set/dict comprehensions.
Author-email: Adam Johnson <me@adamj.eu>
Project-URL: Changelog, https://github.com/adamchainz/flake8-comprehensions/blob/main/CHANGELOG.rst
Project-URL: Funding, https://adamj.eu/books/
Project-URL: Repository, https://github.com/adamchainz/flake8-comprehensions
Keywords: comprehensions,dict comprehension,flake8,list comprehension,set comprehension
Classifier: Development Status :: 5 - Production/Stable
Classifier: Framework :: Flake8
Classifier: Intended Audience :: Developers
Classifier: License :: OSI Approved :: MIT License
Classifier: Natural Language :: English
Classifier: Programming Language :: Python :: 3 :: Only
Classifier: Programming Language :: Python :: 3.9
Classifier: Programming Language :: Python :: 3.10
Classifier: Programming Language :: Python :: 3.11
Classifier: Programming Language :: Python :: 3.12
Classifier: Programming Language :: Python :: 3.13
Classifier: Typing :: Typed
Requires-Python: >=3.9
License-File: LICENSE
Requires-Dist: flake8!=3.2,>=3
